diffpass/__init__.py
diffpass/_modidx.py
diffpass/base.py
diffpass/constants.py
diffpass/data_utils.py
diffpass/entropy_ops.py
diffpass/gumbel_sinkhorn_ops.py
diffpass/ipa_utils.py
diffpass/model.py
diffpass/msa_parsing.py
diffpass/sequence_similarity_ops.py
diffpass/train.py
diffpass-0.2.0.dist-info/LICENSE
diffpass-0.2.0.dist-info/METADATA
diffpass-0.2.0.dist-info/WHEEL
diffpass-0.2.0.dist-info/entry_points.txt
diffpass-0.2.0.dist-info/top_level.txt
diffpass-0.2.0.dist-info/RECORD
