Metadata-Version: 2.1
Name: diffpass
Version: 0.2.0
Summary: Differentiable Pairing using Soft Scores
Home-page: https://github.com/Bitbol-Lab/DiffPaSS
Author: Umberto Lupo and Damiano Sgarbossa
Author-email: umberto.lupo@epfl.ch, damiano.sgarbossa@epfl.ch
License: Apache Software License 2.0
Keywords: nbdev jupyter notebook python
Classifier: Development Status :: 4 - Beta
Classifier: Intended Audience :: Developers
Classifier: Natural Language :: English
Classifier: Programming Language :: Python :: 3.7
Classifier: Programming Language :: Python :: 3.8
Classifier: Programming Language :: Python :: 3.9
Classifier: Programming Language :: Python :: 3.10
Classifier: License :: OSI Approved :: Apache Software License
Requires-Python: >=3.7
License-File: LICENSE
Requires-Dist: torch
Requires-Dist: numpy
Requires-Dist: scipy
Requires-Dist: matplotlib
Requires-Dist: biopython
Requires-Dist: tqdm
Requires-Dist: pandas
Provides-Extra: dev
Requires-Dist: nbdev ; extra == 'dev'
Requires-Dist: black ; extra == 'dev'
Requires-Dist: jupyter ; extra == 'dev'
Requires-Dist: pre-commit ; extra == 'dev'
